cow_file_manager/__init__.py
cow_file_manager/cow_file_manager.py
so_file_system-26.4.5.dist-info/licenses/LICENSE
so_file_system-26.4.5.dist-info/METADATA
so_file_system-26.4.5.dist-info/WHEEL
so_file_system-26.4.5.dist-info/top_level.txt
so_file_system-26.4.5.dist-info/RECORD
