Metadata-Version: 2.4
Name: so-file-system
Version: 26.4.5
Summary: Un sistema de archivos versionado con Copy-on-Write en Python.
Home-page: https://github.com/TuUsuario/so-file-system
Author: TuNombre
Author-email: tunombre@correo.com
Project-URL: Bug Tracker, https://github.com/tuusuario/cow-file-manager/issues
Classifier: Programming Language :: Python :: 3
Classifier: License :: OSI Approved :: MIT License
Classifier: Operating System :: OS Independent
Requires-Python: >=3.8
License-File: LICENSE
Requires-Dist: tqdm
Provides-Extra: dev
Requires-Dist: pytest; extra == "dev"
Dynamic: author
Dynamic: author-email
Dynamic: classifier
Dynamic: description
Dynamic: description-content-type
Dynamic: home-page
Dynamic: license-file
Dynamic: requires-dist
Dynamic: requires-python
Dynamic: summary
